{
    "totalTextureUsage": {
        "value": 3152544287,
        "source": "eN7ity's avatar Samara"
    },
    "totalPolygons": {
        "value": 14791598,
        "source": "Un delivery's avatar emiya komano"
    },
    "boundsLongest": {
        "value": 5930272300,
        "source": "Arbiter_King500's avatar Musketeers˸ Gravestone Mimic"
    },
    "skinnedMeshCount": {
        "value": 1025,
        "source": "Dannyfewie's avatar 미친 여자"
    },
    "meshCount": {
        "value": 6957,
        "source": "candcejohnson's avatar laughing coffin public"
    },
    "materialSlotsUsed": {
        "value": 10743,
        "source": "Un delivery's avatar emiya komano"
    },
    "materialCount": {
        "value": 837,
        "source": "Repentless666's avatar Spawn of Satan"
    },
    "physBoneComponentCount": {
        "value": 445,
        "source": "Neixus's avatar 不可以涩涩"
    },
    "physBoneTransformCount": {
        "value": 5382,
        "source": "泽野弘零's avatar 小白玉-猫"
    },
    "physBoneColliderCount": {
        "value": 211,
        "source": "sᴇɴʏᴀ's avatar Nokk？"
    },
    "physBoneCollisionCheckCount": {
        "value": 21967,
        "source": "ᵕ˘ᴋᴀɪxxᴠɪɪ˘ᵕ's avatar ᴊᴇᴀɴɴᴀ"
    },
    "contactCount": {
        "value": 249,
        "source": "Razz ChaosHowl's avatar Combat System V2 Test"
    },
    "constraintCount": {
        "value": 2662,
        "source": "Jonnytest's avatar karmaf"
    },
    "constraintDepth": {
        "value": 2662,
        "source": "Jonnytest's avatar karmaf"
    },
    "animatorCount": {
        "value": 1808,
        "source": "milkeys_69's avatar ghostbuster"
    },
    "boneCount": {
        "value": 8489,
        "source": "༒ȶʀɨƈӄֆȶɛʀ༒'s avatar WIPP"
    },
    "lightCount": {
        "value": 60000042,
        "source": "ǃRaidenǃ's avatar hajime"
    },
    "particleSystemCount": {
        "value": 1812,
        "source": "undefined's avatar （Patreon Only） Obliteration Nardoragon - Arti"
    },
    "totalMaxParticles": {
        "value": 345744868169,
        "source": "Call Me Sleepy's avatar Personal"
    },
    "meshParticleMaxPolygons": {
        "value": 35303500698,
        "source": "KimeraJin's avatar AdylitKiggy"
    },
    "trailRendererCount": {
        "value": 511,
        "source": "Owen007's avatar Anakin Owen"
    },
    "lineRendererCount": {
        "value": 20,
        "source": "webbtail245's avatar Leon Scott Kennedy （Resident Evil 4）"
    },
    "clothCount": {
        "value": 11,
        "source": "ω I Ł Ł I's avatar Maya Animations"
    },
    "totalClothVertices": {
        "value": 18052,
        "source": "-Rekka-'s avatar maomao˸3"
    },
    "physicsColliders": {
        "value": 1728,
        "source": "milkeys_69's avatar ghostbuster"
    },
    "physicsRigidbodies": {
        "value": 205,
        "source": "PotatoStrangler's avatar The Funniest Valentine"
    },
    "audioSourceCount": {
        "value": 14002,
        "source": "classіst's avatar Pawn"
    },
    "raycastCount": {
        "value": 6,
        "source": "Nexal's avatar ReinheitWB ［VRC3․0-S］"
    },
    "blendShapeCount": {
        "value": 9443,
        "source": "náví's avatar heh"
    },
    "cameraCount": {
        "value": 150,
        "source": "〔るぅ〕's avatar LuminAs_Deceit"
    },
    "uncompressedSize": {
        "value": 524252003,
        "source": "EquusDaemonium's avatar Yeen"
    },
    "fileSize": {
        "value": 208682857,
        "source": "Kingnaldo's avatar Super Manuka Public"
    }
}